{"frames":{"add_picture.png":{"frame":{"h":748,"idx":0,"w":584,"x":0,"y":0},"sourceSize":{"h":748,"w":584},"spriteSourceSize":{"x":0,"y":0}},"add_reward.png":{"frame":{"h":75,"idx":0,"w":150,"x":0,"y":749},"sourceSize":{"h":75,"w":150},"spriteSourceSize":{"x":0,"y":0}},"blank.png":{"frame":{"h":10,"idx":0,"w":10,"x":663,"y":307},"sourceSize":{"h":10,"w":10},"spriteSourceSize":{"x":0,"y":0}},"btn.png":{"frame":{"h":112,"idx":0,"w":99,"x":708,"y":96},"sourceSize":{"h":112,"w":99},"spriteSourceSize":{"x":0,"y":0}},"btn_back.png":{"frame":{"h":122,"idx":0,"w":122,"x":585,"y":96},"sourceSize":{"h":122,"w":122},"spriteSourceSize":{"x":0,"y":0}},"btn_background.png":{"frame":{"h":96,"idx":0,"w":68,"x":663,"y":322},"sourceSize":{"h":96,"w":68},"spriteSourceSize":{"x":0,"y":0}},"btn_bullet.png":{"frame":{"h":96,"idx":0,"w":64,"x":585,"y":404},"sourceSize":{"h":96,"w":64},"spriteSourceSize":{"x":0,"y":0}},"btn_cannon.png":{"frame":{"h":96,"idx":0,"w":77,"x":585,"y":307},"sourceSize":{"h":96,"w":77},"spriteSourceSize":{"x":0,"y":0}},"btn_lock.png":{"frame":{"h":112,"idx":0,"w":99,"x":708,"y":209},"sourceSize":{"h":112,"w":99},"spriteSourceSize":{"x":0,"y":0}},"btn_sound.png":{"frame":{"h":64,"idx":0,"w":64,"x":304,"y":749},"sourceSize":{"h":64,"w":64},"spriteSourceSize":{"x":0,"y":0}},"btn_start.png":{"frame":{"h":95,"idx":0,"w":256,"x":585,"y":0},"sourceSize":{"h":95,"w":256},"spriteSourceSize":{"x":0,"y":0}},"btn_vibration.png":{"frame":{"h":64,"idx":0,"w":64,"x":369,"y":749},"sourceSize":{"h":64,"w":64},"spriteSourceSize":{"x":0,"y":0}},"close.png":{"frame":{"h":64,"idx":0,"w":64,"x":434,"y":749},"sourceSize":{"h":64,"w":64},"spriteSourceSize":{"x":0,"y":0}},"get_diamond.png":{"frame":{"h":56,"idx":0,"w":152,"x":151,"y":749},"sourceSize":{"h":56,"w":152},"spriteSourceSize":{"x":0,"y":0}},"hand_right.png":{"frame":{"h":87,"idx":0,"w":104,"x":585,"y":219},"sourceSize":{"h":87,"w":104},"spriteSourceSize":{"x":0,"y":0}},"icon_diamond.png":{"frame":{"h":55,"idx":0,"w":64,"x":499,"y":749},"sourceSize":{"h":55,"w":64},"spriteSourceSize":{"x":0,"y":0}}},"meta":{"image":"home.png","prefix":"res/ui/home/"}}